mongodb_excel_operation/__init__.py
mongodb_excel_operation/mongodb_excel_operation.py
mongodb_excel_operation-1.1.2.dist-info/LICENSE
mongodb_excel_operation-1.1.2.dist-info/METADATA
mongodb_excel_operation-1.1.2.dist-info/WHEEL
mongodb_excel_operation-1.1.2.dist-info/top_level.txt
mongodb_excel_operation-1.1.2.dist-info/RECORD
